lab9/verilog/adder.v
/*
 * 
 * Lab 9, EECE-144, Two-Bit Adder in Verilog
 *
 * To compile this file run:
 *
 *   iverilog this_file.v
 *
 * Run the executable:
 *
 *   ./a.out
 * OR
 *   vvp a.out
 *
 * Because $dumpfile and $dumpvars have been
 * added it will generate data for gtkwave
 * in some_file.vcd.
 *
 * This output file can then be shown with Gtkwave.
 *
 *   gtkwave some_file.vcd
 *
 * And from within Gtkwave you can pick and choose
 * variables to see their waveforms over time.
 */

// 'adder' is written in a "data flow modeling" style
// using primitives (and(), or(), ...) and operators(&, |, ~, ...)
// It is mostly written using operators in this case.
module adder(input a1,a0,b1, b0, output c, s1, s0);
    assign c =    (a1 & b1)
                | (a0 & b1 & b0) | (a1 & a0 & b0) ;

    assign s1 =   (a1 & ~b1 & ~b0)
                | (a1 & ~a0 & ~b1)
                | (a1 & a0 & b1 & b0)
                | (~a1 & a0 & ~b1 & b0)
                | (~a1 & ~a0 & b1)
                | (~a1 & b1 & ~b0);

    //assign s0 = (a0 & (~b0))| ((~a0) & b0); 
    // simplifies to an XOR
    //assign s0 = a0 ^ b0;
    xor(s0, a0, b0);
endmodule

module test;
    reg a1_in, a0_in, b1_in, b0_in;
	integer i;
    wire c_out, s1_out, s0_out;

     // Dont think of modules as being "called" as in C. 
     // Instead think of this like soldering a chip to a board.
    adder adder1(.a1(a1_in), .a0(a0_in), .b1(b1_in), .b0(b0_in),
                    .c(c_out), .s1(s1_out), .s0(s0_out));

    initial begin
        // produce output for GTKWave
        $dumpfile("gtkwave-02.vcd");
        $dumpvars(0,test);

        // header for the formatted output
        $display("a1 a0 b1 b0 | c s1 s0");
        $display("---------------------");

		for (i = 0; i < 16; i = i + 1) begin
				#1 {a1_in, a0_in, b1_in, b0_in} = i;
				#1 $display("%b  %b  %b  %b  | %b  %b  %b",
                	a1_in, a0_in, b1_in, b0_in, c_out, s1_out, s0_out);
		end
	end
endmodule

lab9/verilog/gtkwave-02.vcd
$date
	Fri Oct 28 23:06:30 2011
$end
$version
	Icarus Verilog
$end
$timescale
	1s
$end
$scope module test $end
$var wire 1 ! c_out $end
$var wire 1 " s0_out $end
$var wire 1 # s1_out $end
$var reg 1 $ a0_in $end
$var reg 1 % a1_in $end
$var reg 1 & b0_in $end
$var reg 1 ' b1_in $end
$var integer 32 ( i [31:0] $end
$scope module adder1 $end
$var wire 1 ) a0 $end
$var wire 1 * a1 $end
$var wire 1 + b0 $end
$var wire 1 , b1 $end
$var wire 1 ! c $end
$var wire 1 " s0 $end
$var wire 1 # s1 $end
$upscope $end
$upscope $end
$enddefinitions $end
#0
$dumpvars
x,
x+
x*
x)
b0 (
x'
x&
x%
x$
x#
x"
x!
$end
#1
0#
0!
0"
0%
0*
0$
0)
0'
0,
0&
0+
#2
b1 (
#3
1"
1&
1+
#4
b10 (
#5
1#
0"
1'
1,
0&
0+
#6
b11 (
#7
1"
1&
1+
#8
b100 (
#9
0#
1$
1)
0'
0,
0&
0+
#10
b101 (
#11
1#
0"
1&
1+
#12
b110 (
#13
1"
1'
1,
0&
0+
#14
b111 (
#15
1!
0#
0"
1&
1+
#16
b1000 (
#17
1#
0!
1%
1*
0$
0)
0'
0,
0&
0+
#18
b1001 (
#19
1"
1&
1+
#20
b1010 (
#21
0#
1!
0"
1'
1,
0&
0+
#22
b1011 (
#23
1"
1&
1+
#24
b1100 (
#25
1#
0!
1$
1)
0'
0,
0&
0+
#26
b1101 (
#27
0#
1!
0"
1&
1+
#28
b1110 (
#29
0#
1!
1"
1'
1,
0&
0+
#30
b1111 (
#31
1#
0"
1&
1+
#32
b10000 (
